scrapy_domain_delay/__init__.py
scrapy_domain_delay/extensions.py
scrapy_custom_delay-0.0.2.dist-info/METADATA
scrapy_custom_delay-0.0.2.dist-info/WHEEL
scrapy_custom_delay-0.0.2.dist-info/top_level.txt
scrapy_custom_delay-0.0.2.dist-info/RECORD
