Metadata-Version: 2.1
Name: scrapy-custom-delay
Version: 0.0.2
Summary: This package provides a way to let you set different delay for different website, using the Scrapy framework.
Author: LiuXiaotong
Author-email: lxtxiaotong@foxmail.com
Project-URL: Source, https://github.com/653603927/scrapy-custom-delay
Classifier: Framework :: Scrapy
Classifier: Intended Audience :: Developers
Classifier: Programming Language :: Python :: 3.10
Classifier: Topic :: Software Development :: Libraries :: Python Modules
Requires-Python: >=3.7
Requires-Dist: scrapy (>=1.6.0)
